{
  "parent": "quest_giver:quest_0014_01",
  "reputation": 10,
  "icon": "minecraft:emerald",
  "start": {
    "title": {
      "text": "Already Done!"
    },
    "description": {
      "text": "哦？在我給你地圖之前你就已經打敗了眼球持有者了？嗯... 讓我看看眼球持有者當時掉落的那隻眼睛。 事實上，丟掉它然後再撿起來...... 不要問為什麼！"
    }
  },
  "complete": {
    "title": {
      "text": "The End of the Road"
    },
    "description": {
      "text": "I have no more information to give you my friend. Follow your calling."
    }
  },
  "tasks": [
    {
      "item": {
        "item": "endrem:corrupted_eye"
      },
      "id": "quest_giver:item_pickup",
      "times": 1
    }
  ]
}