{
  "parent": "quest_giver:quest_0030_01b",
  "reputation": 12,
  "icon": "minecraft:iron_helmet",
  "start": {
    "title": {
      "text": "製作高爐"
    },
    "description": {
      "text": "嘿。你已經製作好高爐了嗎？確保製作一個新的而不是搶別人的！"
    }
  },
  "complete": {
    "title": {
      "text": "太好了！"
    },
    "description": {
      "text": "太好了！有了這個新設備，我可以製作更好的裝備。謝謝！"
    }
  },
  "tasks": [
    {
      "item": {
        "item": "minecraft:blast_furnace"
      },
      "id": "quest_giver:craft",
      "times": 1
    },
    {
      "item": {
        "item": "minecraft:blast_furnace"
      },
      "id": "quest_giver:gift",
      "times": 1
    }
  ],
  "rewards": [
    {
      "command": "/advancement grant @p only custom:trade_armorer",
      "id": "quest_giver:command"
    },
    {
      "command": "/addreputation reputation:villager @p 2",
      "id": "quest_giver:command"
    }
  ]
}