{
  "parent": "quest_giver:root",
  "reputation": 10,
  "icon": "minecraft:white_wool",
  "start": {
    "title": {
      "text": "所以？"
    },
    "description": {
      "text": "給我 10 顆綠寶石，我就教你如何使用織布機！"
    }
  },
  "complete": {
    "title": {
      "text": "謝謝！"
    },
    "description": {
      "text": "給你！"
    }
  },
  "tasks": [
    {
      "item": {
        "item": "minecraft:emerald"
      },
      "id": "quest_giver:gift",
      "times": 10
    }
  ],
  "rewards": [
    {
      "command": "/pmmo admin @p add agility level 1",
      "id": "quest_giver:command"
    }
  ]
}