{
	"parent": "quest_giver:quest_0083_01",
	"reputation": 13,
	"icon": "minecraft:iron_axe",
	"start": {
		"title": {
			"text": "那麼？"
		},
		"description": {
			"text": "你有給我找到鐵斧嗎？趕緊的。"
		}
	},
	"complete": {
		"title": {
			"text": "謝了！"
		},
		"description": {
			"text": "是的！這就是我做的斧頭...，我從未能夠做的比這把更好，你知道。無論如何，這是你的獎勵。我感激你的幫助。"
		}
	},
	"tasks": [
		{
			"item": {
				"item": "minecraft:iron_axe",
				"forge:nbt": "{tag:\"toolsmith\"}"
			},
			"id": "quest_giver:gift",
			"times": 1
		}
	],
	"rewards": [
		{
			"item": {
				"item": "minecraft:emerald"
			},
			"id": "quest_giver:item",
			"times": 2
		},
		{
			"command": "/addreputation reputation:villager @p 2",
			"id": "quest_giver:command"
		},
		{
			"command": "/give @p iron_axe{Enchantments:[{id:efficiency,lvl:2}]}",
			"id": "quest_giver:command"
		},
		{
			"command": "/advancement grant @p only custom:trade_toolsmith",
			"id": "quest_giver:command"
		}
	]
}